kinopoisk/__init__.py
kinopoisk/__init__.pyc
kinopoisk/request.py
kinopoisk/request.pyc
kinopoisk/utils.py
kinopoisk/utils.pyc
kinopoisk/__pycache__/__init__.cpython-37.pyc
kinopoisk/__pycache__/__init__.cpython-39.pyc
kinopoisk/__pycache__/request.cpython-37.pyc
kinopoisk/__pycache__/request.cpython-39.pyc
kinopoisk/__pycache__/utils.cpython-37.pyc
kinopoisk/__pycache__/utils.cpython-39.pyc
kinopoisk/movie/__init__.py
kinopoisk/movie/__init__.pyc
kinopoisk/movie/sources.py
kinopoisk/movie/sources.pyc
kinopoisk/movie/__pycache__/__init__.cpython-37.pyc
kinopoisk/movie/__pycache__/__init__.cpython-39.pyc
kinopoisk/movie/__pycache__/sources.cpython-37.pyc
kinopoisk/movie/__pycache__/sources.cpython-39.pyc
kinopoisk/person/__init__.py
kinopoisk/person/__init__.pyc
kinopoisk/person/sources.py
kinopoisk/person/sources.pyc
kinopoisk/person/__pycache__/__init__.cpython-37.pyc
kinopoisk/person/__pycache__/__init__.cpython-39.pyc
kinopoisk/person/__pycache__/sources.cpython-37.pyc
kinopoisk/person/__pycache__/sources.cpython-39.pyc
kinopoisk/tests/__init__.py
kinopoisk/tests/__init__.pyc
kinopoisk/tests/__main__.py
kinopoisk/tests/base.py
kinopoisk/tests/base.pyc
kinopoisk/tests/movie.py
kinopoisk/tests/movie.pyc
kinopoisk/tests/person.py
kinopoisk/tests/person.pyc
kinopoisk/tests/__pycache__/__init__.cpython-37.pyc
kinopoisk/tests/__pycache__/__init__.cpython-39.pyc
kinopoisk/tests/__pycache__/__main__.cpython-37.pyc
kinopoisk/tests/__pycache__/__main__.cpython-39.pyc
kinopoisk/tests/__pycache__/base.cpython-37.pyc
kinopoisk/tests/__pycache__/base.cpython-39.pyc
kinopoisk/tests/__pycache__/movie.cpython-37.pyc
kinopoisk/tests/__pycache__/movie.cpython-39.pyc
kinopoisk/tests/__pycache__/person.cpython-37.pyc
kinopoisk/tests/__pycache__/person.cpython-39.pyc
kinopoisk/tests/cassettes/MovieTest.test_movie_by_id_1552.yaml
kinopoisk/tests/cassettes/MovieTest.test_movie_cast.yaml
kinopoisk/tests/cassettes/MovieTest.test_movie_cast_1.yaml
kinopoiskpy-0.9.0.dist-info/LICENSE
kinopoiskpy-0.9.0.dist-info/METADATA
kinopoiskpy-0.9.0.dist-info/WHEEL
kinopoiskpy-0.9.0.dist-info/top_level.txt
kinopoiskpy-0.9.0.dist-info/RECORD
