Metadata-Version: 2.1
Name: kinopoiskpy
Version: 0.9.0
Summary: Python API to kinopoisk.ru
Home-page: https://github.com/ramusus/kinopoiskpy
Author: ramusus
Author-email: ramusus@gmail.com
License: BSD
Download-URL: http://pypi.python.org/pypi/kinopoiskpy
Platform: UNKNOWN
Classifier: Development Status :: 4 - Beta
Classifier: Environment :: Web Environment
Classifier: Intended Audience :: Developers
Classifier: License :: OSI Approved :: BSD License
Classifier: Operating System :: OS Independent
Classifier: Programming Language :: Python
Classifier: Topic :: Software Development :: Libraries :: Python Modules
License-File: LICENSE
Requires-Dist: beautifulsoup4
Requires-Dist: lxml
Requires-Dist: requests
Requires-Dist: simplejson
Requires-Dist: python-dateutil
Requires-Dist: future
